{
  "summary": {
    "study_name": "auto_optimization_20250729_002658",
    "start_time": "2025-07-29 08:27:21.670480",
    "total_trials": 1500,
    "completed_trials": 1500,
    "failed_trials": 0,
    "pruned_trials": 0,
    "full_optimization": true
  },
  "best_result": {
    "trial_number": 985,
    "value": 1.0008163898597535,
    "parameters": {
      "coint_pvalue_threshold": 0.1257020949000932,
      "lookback_days": 45,
      "max_hurst_exponent": 0.3842590321311966,
      "min_half_life_days": 2.1507611755945137,
      "max_half_life_days": 16,
      "min_mean_crossings": 7,
      "ssd_top_n": 1000,
      "pvalue_top_n": 350,
      "zscore_threshold": 0.804884067459106,
      "zscore_exit": 0.7710824053600542,
      "rolling_window": 25,
      "max_active_positions": 20,
      "risk_per_position_pct": 0.02176863512700554,
      "max_position_size_pct": 0.07739909882189641,
      "stop_loss_multiplier": 4.193996070950698,
      "time_stop_multiplier": 5.4309566597627565,
      "commission_pct": 0.00031481140665024816,
      "slippage_pct": 0.0003904940093695472,
      "cooldown_hours": 10,
      "normalization_method": "zscore",
      "min_history_ratio": 0.7869137750285322
    }
  },
  "statistics": {
    "mean": -2.57767573865459,
    "median": -5.0,
    "std": 2.7084881458307635,
    "min": -5.0,
    "max": 1.0008163898597535,
    "q25": -5.0,
    "q75": 0.5049636733279023
  },
  "top_10_trials": [
    {
      "number": 985,
      "value": 1.0008163898597535,
      "state": "1",
      "params": {
        "coint_pvalue_threshold": 0.1257020949000932,
        "lookback_days": 45,
        "max_hurst_exponent": 0.3842590321311966,
        "min_half_life_days": 2.1507611755945137,
        "max_half_life_days": 16,
        "min_mean_crossings": 7,
        "ssd_top_n": 1000,
        "pvalue_top_n": 350,
        "zscore_threshold": 0.804884067459106,
        "zscore_exit": 0.7710824053600542,
        "rolling_window": 25,
        "max_active_positions": 20,
        "risk_per_position_pct": 0.02176863512700554,
        "max_position_size_pct": 0.07739909882189641,
        "stop_loss_multiplier": 4.193996070950698,
        "time_stop_multiplier": 5.4309566597627565,
        "commission_pct": 0.00031481140665024816,
        "slippage_pct": 0.0003904940093695472,
        "cooldown_hours": 10,
        "normalization_method": "zscore",
        "min_history_ratio": 0.7869137750285322
      },
      "datetime_start": "2025-07-29 05:39:27.194660",
      "datetime_complete": "2025-07-29 05:40:09.342860",
      "duration": "0:00:42.148200"
    },
    {
      "number": 987,
      "value": 1.0001874624430311,
      "state": "1",
      "params": {
        "coint_pvalue_threshold": 0.13048650985994395,
        "lookback_days": 75,
        "max_hurst_exponent": 0.3829338215979651,
        "min_half_life_days": 1.3473198584277415,
        "max_half_life_days": 14,
        "min_mean_crossings": 13,
        "ssd_top_n": 1000,
        "pvalue_top_n": 100,
        "zscore_threshold": 0.8036493518664272,
        "zscore_exit": 0.7878973334497192,
        "rolling_window": 25,
        "max_active_positions": 10,
        "risk_per_position_pct": 0.026445146876636842,
        "max_position_size_pct": 0.17544889532314573,
        "stop_loss_multiplier": 5.265715363626739,
        "time_stop_multiplier": 4.8868278724564576,
        "commission_pct": 0.0006685683545070838,
        "slippage_pct": 0.0004862006610252187,
        "cooldown_hours": 11,
        "normalization_method": "minmax",
        "min_history_ratio": 0.4457683223661403
      },
      "datetime_start": "2025-07-29 05:40:09.603825",
      "datetime_complete": "2025-07-29 05:40:52.153170",
      "duration": "0:00:42.549345"
    },
    {
      "number": 301,
      "value": 0.993122913265694,
      "state": "1",
      "params": {
        "coint_pvalue_threshold": 0.11865648582103991,
        "lookback_days": 90,
        "max_hurst_exponent": 0.47727787135892236,
        "min_half_life_days": 1.979792925316243,
        "max_half_life_days": 22,
        "min_mean_crossings": 7,
        "ssd_top_n": 1000,
        "pvalue_top_n": 100,
        "zscore_threshold": 0.8182992780841691,
        "zscore_exit": 0.7943929576607016,
        "rolling_window": 25,
        "max_active_positions": 10,
        "risk_per_position_pct": 0.027547573185633934,
        "max_position_size_pct": 0.07962842944985031,
        "stop_loss_multiplier": 4.1675104902579,
        "time_stop_multiplier": 6.0771598469471915,
        "commission_pct": 0.0005095021739980983,
        "slippage_pct": 0.0005563770343261803,
        "cooldown_hours": 4,
        "normalization_method": "minmax",
        "min_history_ratio": 0.8662868851345061
      },
      "datetime_start": "2025-07-29 01:45:42.447466",
      "datetime_complete": "2025-07-29 01:46:25.251541",
      "duration": "0:00:42.804075"
    },
    {
      "number": 1260,
      "value": 0.9721857294799647,
      "state": "1",
      "params": {
        "coint_pvalue_threshold": 0.09973731208671727,
        "lookback_days": 30,
        "max_hurst_exponent": 0.33554912062831393,
        "min_half_life_days": 2.8113216256309452,
        "max_half_life_days": 13,
        "min_mean_crossings": 7,
        "ssd_top_n": 1000,
        "pvalue_top_n": 100,
        "zscore_threshold": 0.8219286683055794,
        "zscore_exit": 0.7880357396309634,
        "rolling_window": 25,
        "max_active_positions": 15,
        "risk_per_position_pct": 0.02517553233930897,
        "max_position_size_pct": 0.06918092668270798,
        "stop_loss_multiplier": 3.1271977182250765,
        "time_stop_multiplier": 4.9469448346358185,
        "commission_pct": 0.000641004212047509,
        "slippage_pct": 0.0007428222930237482,
        "cooldown_hours": 1,
        "normalization_method": "zscore",
        "min_history_ratio": 0.8153131409470552
      },
      "datetime_start": "2025-07-29 07:17:31.708490",
      "datetime_complete": "2025-07-29 07:18:14.345935",
      "duration": "0:00:42.637445"
    },
    {
      "number": 1193,
      "value": 0.9556943876764596,
      "state": "1",
      "params": {
        "coint_pvalue_threshold": 0.10092445743044001,
        "lookback_days": 75,
        "max_hurst_exponent": 0.47524809535867135,
        "min_half_life_days": 2.5837599741136716,
        "max_half_life_days": 28,
        "min_mean_crossings": 11,
        "ssd_top_n": 1000,
        "pvalue_top_n": 300,
        "zscore_threshold": 0.8192742412285657,
        "zscore_exit": 0.7670509401653454,
        "rolling_window": 25,
        "max_active_positions": 5,
        "risk_per_position_pct": 0.012949736228726808,
        "max_position_size_pct": 0.1766586297859744,
        "stop_loss_multiplier": 5.6461970672144,
        "time_stop_multiplier": 9.317877030630308,
        "commission_pct": 0.00021850779844611093,
        "slippage_pct": 0.0007976729580514791,
        "cooldown_hours": 2,
        "normalization_method": "minmax",
        "min_history_ratio": 0.8658842606388816
      },
      "datetime_start": "2025-07-29 06:53:44.989731",
      "datetime_complete": "2025-07-29 06:54:27.610571",
      "duration": "0:00:42.620840"
    },
    {
      "number": 1003,
      "value": 0.9552284401657083,
      "state": "1",
      "params": {
        "coint_pvalue_threshold": 0.1389349040266587,
        "lookback_days": 90,
        "max_hurst_exponent": 0.41689478533124763,
        "min_half_life_days": 1.363722639782593,
        "max_half_life_days": 29,
        "min_mean_crossings": 15,
        "ssd_top_n": 1000,
        "pvalue_top_n": 250,
        "zscore_threshold": 0.8053208003808043,
        "zscore_exit": 0.7221138855851688,
        "rolling_window": 20,
        "max_active_positions": 15,
        "risk_per_position_pct": 0.02574584568446702,
        "max_position_size_pct": 0.1493352867516975,
        "stop_loss_multiplier": 2.1935096404671226,
        "time_stop_multiplier": 7.183901995881248,
        "commission_pct": 0.0007296160599848597,
        "slippage_pct": 0.0007697460715255866,
        "cooldown_hours": 9,
        "normalization_method": "minmax",
        "min_history_ratio": 0.4237453317750015
      },
      "datetime_start": "2025-07-29 05:44:28.242564",
      "datetime_complete": "2025-07-29 05:45:09.747043",
      "duration": "0:00:41.504479"
    },
    {
      "number": 902,
      "value": 0.9546019355004991,
      "state": "1",
      "params": {
        "coint_pvalue_threshold": 0.11763354336719549,
        "lookback_days": 90,
        "max_hurst_exponent": 0.39367315218569304,
        "min_half_life_days": 1.9328562120965003,
        "max_half_life_days": 11,
        "min_mean_crossings": 7,
        "ssd_top_n": 1000,
        "pvalue_top_n": 450,
        "zscore_threshold": 0.8017382062276592,
        "zscore_exit": 0.7423825617540412,
        "rolling_window": 20,
        "max_active_positions": 10,
        "risk_per_position_pct": 0.02770523819129579,
        "max_position_size_pct": 0.1443849372408447,
        "stop_loss_multiplier": 5.293141893109476,
        "time_stop_multiplier": 7.399649783124876,
        "commission_pct": 0.0007510261157417167,
        "slippage_pct": 0.000620717453266015,
        "cooldown_hours": 8,
        "normalization_method": "minmax",
        "min_history_ratio": 0.7367032518728173
      },
      "datetime_start": "2025-07-29 05:09:19.304507",
      "datetime_complete": "2025-07-29 05:10:01.875377",
      "duration": "0:00:42.570870"
    },
    {
      "number": 1114,
      "value": 0.9521195289706053,
      "state": "1",
      "params": {
        "coint_pvalue_threshold": 0.11611801345419748,
        "lookback_days": 75,
        "max_hurst_exponent": 0.4833593300302192,
        "min_half_life_days": 1.4677405317813488,
        "max_half_life_days": 28,
        "min_mean_crossings": 15,
        "ssd_top_n": 1000,
        "pvalue_top_n": 50,
        "zscore_threshold": 0.8184931094241179,
        "zscore_exit": 0.7578727812906131,
        "rolling_window": 25,
        "max_active_positions": 20,
        "risk_per_position_pct": 0.02939095845500095,
        "max_position_size_pct": 0.08778615427742192,
        "stop_loss_multiplier": 6.782381656896339,
        "time_stop_multiplier": 6.21170246148372,
        "commission_pct": 0.00029494705228151245,
        "slippage_pct": 0.0007849988317450082,
        "cooldown_hours": 4,
        "normalization_method": "minmax",
        "min_history_ratio": 0.7243101155477022
      },
      "datetime_start": "2025-07-29 06:29:22.066346",
      "datetime_complete": "2025-07-29 06:30:04.699085",
      "duration": "0:00:42.632739"
    },
    {
      "number": 1169,
      "value": 0.9518246351228603,
      "state": "1",
      "params": {
        "coint_pvalue_threshold": 0.12869287854795022,
        "lookback_days": 45,
        "max_hurst_exponent": 0.35670519822828994,
        "min_half_life_days": 2.1108930120023675,
        "max_half_life_days": 18,
        "min_mean_crossings": 11,
        "ssd_top_n": 1000,
        "pvalue_top_n": 300,
        "zscore_threshold": 0.8229362944421844,
        "zscore_exit": 0.77234987407389,
        "rolling_window": 25,
        "max_active_positions": 15,
        "risk_per_position_pct": 0.02106604130571149,
        "max_position_size_pct": 0.1422764070003173,
        "stop_loss_multiplier": 3.5290859543836186,
        "time_stop_multiplier": 5.731511905536124,
        "commission_pct": 0.000536454485046831,
        "slippage_pct": 0.0006584151570127663,
        "cooldown_hours": 8,
        "normalization_method": "minmax",
        "min_history_ratio": 0.5603432371349372
      },
      "datetime_start": "2025-07-29 06:48:42.108717",
      "datetime_complete": "2025-07-29 06:49:24.453458",
      "duration": "0:00:42.344741"
    },
    {
      "number": 1312,
      "value": 0.9404780584708068,
      "state": "1",
      "params": {
        "coint_pvalue_threshold": 0.05911786098918287,
        "lookback_days": 30,
        "max_hurst_exponent": 0.33823463673613463,
        "min_half_life_days": 2.788388911649259,
        "max_half_life_days": 31,
        "min_mean_crossings": 15,
        "ssd_top_n": 1000,
        "pvalue_top_n": 200,
        "zscore_threshold": 0.8048176259639113,
        "zscore_exit": 0.6636343685880648,
        "rolling_window": 25,
        "max_active_positions": 10,
        "risk_per_position_pct": 0.015817374339777302,
        "max_position_size_pct": 0.17510958565404608,
        "stop_loss_multiplier": 5.2761455063751095,
        "time_stop_multiplier": 3.7762945326315642,
        "commission_pct": 0.00029444313265884406,
        "slippage_pct": 0.000475464234459364,
        "cooldown_hours": 5,
        "normalization_method": "zscore",
        "min_history_ratio": 0.857747377817844
      },
      "datetime_start": "2025-07-29 07:36:08.961130",
      "datetime_complete": "2025-07-29 07:36:51.853564",
      "duration": "0:00:42.892434"
    }
  ],
  "parameter_importance": [
    {
      "parameter": "rolling_window",
      "correlation": -0.6824186124489516,
      "abs_correlation": 0.6824186124489516,
      "mean_value": 30.513392857142858,
      "std_value": 12.532989520673588,
      "min_value": 20.0,
      "max_value": 80.0
    },
    {
      "parameter": "zscore_exit",
      "correlation": 0.5530454491075261,
      "abs_correlation": 0.5530454491075261,
      "mean_value": 0.6417481112059017,
      "std_value": 0.13664185260257136,
      "min_value": 0.021093579597801605,
      "max_value": 0.7998581198038108
    },
    {
      "parameter": "zscore_threshold",
      "correlation": -0.5054873540581015,
      "abs_correlation": 0.5054873540581015,
      "mean_value": 1.1198228117437523,
      "std_value": 0.31879261981706564,
      "min_value": 0.8001383108030502,
      "max_value": 2.474535675429713
    },
    {
      "parameter": "coint_pvalue_threshold",
      "correlation": 0.23116872657984766,
      "abs_correlation": 0.23116872657984766,
      "mean_value": 0.10453256752409157,
      "std_value": 0.03234820044638282,
      "min_value": 0.011970321772286793,
      "max_value": 0.14997142215737438
    },
    {
      "parameter": "slippage_pct",
      "correlation": 0.21989752205061866,
      "abs_correlation": 0.21989752205061866,
      "mean_value": 0.0005712724656301083,
      "std_value": 0.00016307707224414822,
      "min_value": 0.0001012996764968175,
      "max_value": 0.0007997296334691215
    },
    {
      "parameter": "max_hurst_exponent",
      "correlation": -0.1812659770007139,
      "abs_correlation": 0.1812659770007139,
      "mean_value": 0.4322895816214634,
      "std_value": 0.07968353644823566,
      "min_value": 0.3005132729873967,
      "max_value": 0.5997039736147395
    },
    {
      "parameter": "max_active_positions",
      "correlation": -0.1774321944267329,
      "abs_correlation": 0.1774321944267329,
      "mean_value": 12.604166666666666,
      "std_value": 6.1999361004992,
      "min_value": 5.0,
      "max_value": 25.0
    },
    {
      "parameter": "lookback_days",
      "correlation": 0.12078552051686044,
      "abs_correlation": 0.12078552051686044,
      "mean_value": 66.5625,
      "std_value": 20.776985397445493,
      "min_value": 30.0,
      "max_value": 90.0
    },
    {
      "parameter": "stop_loss_multiplier",
      "correlation": 0.08727470643981715,
      "abs_correlation": 0.08727470643981715,
      "mean_value": 5.290639412635257,
      "std_value": 1.636319361115981,
      "min_value": 2.015265651142243,
      "max_value": 7.979331316853716
    },
    {
      "parameter": "max_half_life_days",
      "correlation": -0.08065003080185032,
      "abs_correlation": 0.08065003080185032,
      "mean_value": 23.489583333333332,
      "std_value": 9.141700126191958,
      "min_value": 10.0,
      "max_value": 45.0
    },
    {
      "parameter": "min_history_ratio",
      "correlation": 0.07453060053671497,
      "abs_correlation": 0.07453060053671497,
      "mean_value": 0.7184871037004705,
      "std_value": 0.14007103458965584,
      "min_value": 0.40026668411430294,
      "max_value": 0.8999700531560295
    },
    {
      "parameter": "time_stop_multiplier",
      "correlation": 0.0708735339304053,
      "abs_correlation": 0.0708735339304053,
      "mean_value": 6.038238221263963,
      "std_value": 1.8940406565942902,
      "min_value": 2.221813182131971,
      "max_value": 9.96498926605944
    },
    {
      "parameter": "max_position_size_pct",
      "correlation": -0.05742518477496085,
      "abs_correlation": 0.05742518477496085,
      "mean_value": 0.1271485070367364,
      "std_value": 0.04629234373702002,
      "min_value": 0.05016500323992377,
      "max_value": 0.2495122165144959
    },
    {
      "parameter": "commission_pct",
      "correlation": 0.05681428365914771,
      "abs_correlation": 0.05681428365914771,
      "mean_value": 0.0005214930488943365,
      "std_value": 0.00019197284948088478,
      "min_value": 0.00010182976518806129,
      "max_value": 0.0007991513615755904
    },
    {
      "parameter": "risk_per_position_pct",
      "correlation": 0.05572727451042391,
      "abs_correlation": 0.05572727451042391,
      "mean_value": 0.01996994543430253,
      "std_value": 0.007169692218748484,
      "min_value": 0.005057928586424284,
      "max_value": 0.029999298495870484
    },
    {
      "parameter": "min_half_life_days",
      "correlation": 0.04015111131486409,
      "abs_correlation": 0.04015111131486409,
      "mean_value": 2.144455169041542,
      "std_value": 0.6069870591161316,
      "min_value": 0.5337711371332916,
      "max_value": 2.9959334140322462
    },
    {
      "parameter": "cooldown_hours",
      "correlation": -0.024774537434768047,
      "abs_correlation": 0.024774537434768047,
      "mean_value": 6.348214285714286,
      "std_value": 3.3469335248234273,
      "min_value": 1.0,
      "max_value": 12.0
    },
    {
      "parameter": "min_mean_crossings",
      "correlation": 0.0026142252001686637,
      "abs_correlation": 0.0026142252001686637,
      "mean_value": 9.05952380952381,
      "std_value": 3.7487442602147945,
      "min_value": 3.0,
      "max_value": 15.0
    },
    {
      "parameter": "pvalue_top_n",
      "correlation": 0.0016938575563590892,
      "abs_correlation": 0.0016938575563590892,
      "mean_value": 206.91964285714286,
      "std_value": 124.0782627686072,
      "min_value": 50.0,
      "max_value": 500.0
    },
    {
      "parameter": "ssd_top_n",
      "correlation": NaN,
      "abs_correlation": NaN,
      "mean_value": 1000.0,
      "std_value": 0.0,
      "min_value": 1000.0,
      "max_value": 1000.0
    }
  ],
  "analysis_timestamp": "2025-07-29 08:34:14.776935"
}